serverhub/__init__.py
serverhub/sysinfo.py
serverhub-0.0.2.dist-info/LICENSE.txt
serverhub-0.0.2.dist-info/METADATA
serverhub-0.0.2.dist-info/WHEEL
serverhub-0.0.2.dist-info/entry_points.txt
serverhub-0.0.2.dist-info/top_level.txt
serverhub-0.0.2.dist-info/RECORD
