Metadata-Version: 2.1
Name: serverhub
Version: 0.0.2
Summary: serverhub backend & tools
Home-page: https://github.com/sxwxs/serverhub
Author: sxwxs
Author-email: sxwxs@msn.com
License: UNKNOWN
Project-URL: Bug Reports, https://github.com/sxwxs/serverhub/issues
Project-URL: Funding, https://i.loli.net/2019/12/28/pv8PUd4eKGyNDiV.png
Project-URL: Source, https://github.com/sxwxs/serverhub
Keywords: server monitor ssl
Platform: UNKNOWN
Classifier: Development Status :: 4 - Beta
Classifier: Intended Audience :: Developers
Classifier: Intended Audience :: System Administrators
Classifier: Intended Audience :: Information Technology
Classifier: Topic :: Utilities
Classifier: License :: OSI Approved :: MIT License
Classifier: Programming Language :: Python :: 3
Classifier: Programming Language :: Python :: 3.5
Classifier: Programming Language :: Python :: 3.6
Classifier: Programming Language :: Python :: 3.7
Classifier: Programming Language :: Python :: 3.8
Classifier: Operating System :: POSIX :: Linux
Requires-Python: >=3.5
Requires-Dist: psutil
